lambdex/__init__.py
lambdex/_aliases.py
lambdex/_config.py
lambdex/_exports.py
lambdex/_features.py
lambdex/ast_parser.py
lambdex/keywords.py
lambdex/repl.py
lambdex/compiler/__init__.py
lambdex/compiler/asm.py
lambdex/compiler/cache.py
lambdex/compiler/clauses.py
lambdex/compiler/context.py
lambdex/compiler/core.py
lambdex/compiler/dispatcher.py
lambdex/compiler/error.py
lambdex/compiler/rules.py
lambdex/compiler/asm/__init__.py
lambdex/compiler/asm/core.py
lambdex/compiler/asm/frontend.py
lambdex/compiler/bytecodes/__init__.py
lambdex/compiler/bytecodes/_lambdex_finder.py
lambdex/compiler/bytecodes/modtrans.py
lambdex/fmt/__init__.py
lambdex/fmt/__main__.py
lambdex/fmt/config.py
lambdex/fmt/jobs_meta.py
lambdex/fmt/adapters/__init__.py
lambdex/fmt/adapters/_base.py
lambdex/fmt/adapters/dummy.py
lambdex/fmt/adapters/yapf.py
lambdex/fmt/cli/__init__.py
lambdex/fmt/cli/main.py
lambdex/fmt/cli/mock.py
lambdex/fmt/cli/opts.py
lambdex/fmt/core/__init__.py
lambdex/fmt/core/_stream_base.py
lambdex/fmt/core/api.py
lambdex/fmt/core/definitions/__init__.py
lambdex/fmt/core/definitions/actions.py
lambdex/fmt/core/definitions/annotation.py
lambdex/fmt/core/definitions/btstream.py
lambdex/fmt/core/definitions/context.py
lambdex/fmt/core/definitions/state.py
lambdex/fmt/core/definitions/token.py
lambdex/fmt/core/definitions/token_info.py
lambdex/fmt/core/tkutils/__init__.py
lambdex/fmt/core/tkutils/tokenize.py
lambdex/fmt/core/tkutils/builtins/__init__.py
lambdex/fmt/core/tkutils/builtins/token.py
lambdex/fmt/core/tkutils/builtins/tokenize.py
lambdex/fmt/core/tkutils/rules/__init__.py
lambdex/fmt/core/tkutils/rules/matcher.py
lambdex/fmt/core/tkutils/rules/rules.py
lambdex/fmt/core/transforms/AnnotateLeadingWhitespace.py
lambdex/fmt/core/transforms/AsCode.py
lambdex/fmt/core/transforms/CollectComments.py
lambdex/fmt/core/transforms/DropToken.py
lambdex/fmt/core/transforms/InsertNewline.py
lambdex/fmt/core/transforms/NormalizeWhitespaceBeforeComments.py
pylambdex-1.0.0.dist-info/LICENSE
pylambdex-1.0.0.dist-info/METADATA
pylambdex-1.0.0.dist-info/WHEEL
pylambdex-1.0.0.dist-info/entry_points.txt
pylambdex-1.0.0.dist-info/top_level.txt
pylambdex-1.0.0.dist-info/RECORD
