Metadata-Version: 2.1
Name: pylambdex
Version: 1.0.0
Summary: A library to write multi-line anonymous functions.
Home-page: https://github.com/hsfzxjy/lambdex
Author: Jingyi Xie (hsfzxjy)
Author-email: hsfzxjy@gmail.com
License: GPL-3.0 License
Platform: UNKNOWN
Classifier: Development Status :: 4 - Beta
Classifier: Environment :: Console
Classifier: License :: OSI Approved :: GNU General Public License v3 (GPLv3)
Classifier: Operating System :: OS Independent
Classifier: Programming Language :: Python
Classifier: Programming Language :: Python :: 3 :: Only
Classifier: Programming Language :: Python :: 3.5
Classifier: Programming Language :: Python :: 3.6
Classifier: Programming Language :: Python :: 3.7
Classifier: Programming Language :: Python :: 3.8
Classifier: Programming Language :: Python :: 3.9
Classifier: Programming Language :: Python :: 3.10
Classifier: Programming Language :: Python :: Implementation :: CPython
Classifier: Topic :: Software Development :: Compilers
Classifier: Topic :: Software Development :: Pre-processors
Classifier: Typing :: Typed
Requires-Dist: inquirer (==2.7.0)
